setup.cfg
setup.py
nea_api/__init__.py
nea_api.egg-info/PKG-INFO
nea_api.egg-info/SOURCES.txt
nea_api.egg-info/dependency_links.txt
nea_api.egg-info/requires.txt
nea_api.egg-info/top_level.txt