Metadata-Version: 1.1
Name: nea-api
Version: 0.1.1
Summary: Python Wrapper for NEA.gov.sg's Data API
Home-page: https://github.com/davidchua/nea_api
Author: David Chua
Author-email: zhchua@gmail.com
License: UNKNOWN
Download-URL: https://github.com/davidchua/nea_api/tarball/0.1.1
Keywords: data.gov.sg,python,wrapper,psi,singapore
Platform: UNKNOWN
